torchgather/__init__.py
torchgather/all_gather.py
torchgather/broadcast.py
torchgather-0.2.0.dist-info/METADATA
torchgather-0.2.0.dist-info/WHEEL
torchgather-0.2.0.dist-info/top_level.txt
torchgather-0.2.0.dist-info/RECORD
