Metadata-Version: 2.4
Name: torchgather
Version: 0.2.0
Requires-Python: >=3.10
Requires-Dist: torch
